README.md
setup.py
bot_studio/DataKund.exe
bot_studio/GetAttributes.py
bot_studio/GetData.py
bot_studio/Progress.py
bot_studio/__init__.py
bot_studio/bot_studio.py
bot_studio/dk_studio.py
bot_studio/install.py
bot_studio.egg-info/PKG-INFO
bot_studio.egg-info/SOURCES.txt
bot_studio.egg-info/dependency_links.txt
bot_studio.egg-info/entry_points.txt
bot_studio.egg-info/requires.txt
bot_studio.egg-info/top_level.txt