Metadata-Version: 2.1
Name: bot-studio
Version: 1.4.0
Summary: Automation Library
Home-page: UNKNOWN
Author: DataKund
Author-email: datakund@gmail.com
License: Apache License 2.0
Platform: UNKNOWN
